{
    "success": true,
    "result": [
        {
            "capabilities": {
                "6g": {
                    "shortgi20": false,
                    "vht_rx_ldpc": false,
                    "vht_sounding_dimensions_1": false,
                    "ldpc": false,
                    "ht_40": false,
                    "smps_dynamic": false,
                    "vht_shortgi80": false,
                    "vht_rx_stbc_4": false,
                    "vht_txops_ps": false,
                    "eht_320": false,
                    "eht_supported": false,
                    "vht_max_ampdu_len_exp4": false,
                    "vht_max_ampdu_len_exp6": false,
                    "smps_static": false,
                    "vht_rx_antenna_consistency": false,
                    "vht_shortgi160": false,
                    "he_40": false,
                    "vht_tx_stbc": false,
                    "he_supported": false,
                    "vht_ext_nss_bw_3": false,
                    "delayed_ba": false,
                    "ht_20": false,
                    "vht_ext_nss_bw_2": false,
                    "vht_ext_nss_bw_1": false,
                    "vht_beamformee_sts_1": false,
                    "vht_max_ampdu_len_exp3": false,
                    "vht_su_beamformer": false,
                    "vht_tx_antenna_consistency": false,
                    "he_80": false,
                    "vht_rx_stbc_3": false,
                    "vht_max_ampdu_len_exp7": false,
                    "vht_max_ampdu_len_exp1": false,
                    "he_160": false,
                    "vht_max_ampdu_len_exp5": false,
                    "rx_stbc_3": false,
                    "vht_htc": false,
                    "vht_mpdu_len_11454": false,
                    "vht_max_ampdu_len_exp2": false,
                    "vht_rx_stbc_1": false,
                    "rx_stbc_2": false,
                    "vht_sounding_dimensions_3": false,
                    "max_amsdu_7935": false,
                    "vht_su_beamformee": false,
                    "dsss_cck_40": false,
                    "vht_80_80": false,
                    "vht_160": false,
                    "vht_sounding_dimensions_2": false,
                    "psmp": false,
                    "vht_80": false,
                    "vht_beamformee_sts_3": false,
                    "vht_beamformee_sts_2": false,
                    "supported": false,
                    "greenfield": false,
                    "vht_rx_stbc_2": false,
                    "rx_stbc_1": false,
                    "vht_mu_beamformee": false,
                    "vht_mpdu_len_7991": false,
                    "tx_stbc": false,
                    "shortgi40": false,
                    "vht_mu_beamformer": false,
                    "lsig_txop_prot": false
                },
                "5g": {
                    "shortgi20": false,
                    "vht_rx_ldpc": false,
                    "vht_sounding_dimensions_1": false,
                    "ldpc": false,
                    "ht_40": false,
                    "smps_dynamic": false,
                    "vht_shortgi80": false,
                    "vht_rx_stbc_4": false,
                    "vht_txops_ps": false,
                    "eht_320": false,
                    "eht_supported": false,
                    "vht_max_ampdu_len_exp4": false,
                    "vht_max_ampdu_len_exp6": false,
                    "smps_static": false,
                    "vht_rx_antenna_consistency": false,
                    "vht_shortgi160": false,
                    "he_40": false,
                    "vht_tx_stbc": false,
                    "he_supported": false,
                    "vht_ext_nss_bw_3": false,
                    "delayed_ba": false,
                    "ht_20": false,
                    "vht_ext_nss_bw_2": false,
                    "vht_ext_nss_bw_1": false,
                    "vht_beamformee_sts_1": false,
                    "vht_max_ampdu_len_exp3": false,
                    "vht_su_beamformer": false,
                    "vht_tx_antenna_consistency": false,
                    "he_80": false,
                    "vht_rx_stbc_3": false,
                    "vht_max_ampdu_len_exp7": false,
                    "vht_max_ampdu_len_exp1": false,
                    "he_160": false,
                    "vht_max_ampdu_len_exp5": false,
                    "rx_stbc_3": false,
                    "vht_htc": false,
                    "vht_mpdu_len_11454": false,
                    "vht_max_ampdu_len_exp2": false,
                    "vht_rx_stbc_1": false,
                    "rx_stbc_2": false,
                    "vht_sounding_dimensions_3": false,
                    "max_amsdu_7935": false,
                    "vht_su_beamformee": false,
                    "dsss_cck_40": false,
                    "vht_80_80": false,
                    "vht_160": false,
                    "vht_sounding_dimensions_2": false,
                    "psmp": false,
                    "vht_80": false,
                    "vht_beamformee_sts_3": false,
                    "vht_beamformee_sts_2": false,
                    "supported": false,
                    "greenfield": false,
                    "vht_rx_stbc_2": false,
                    "rx_stbc_1": false,
                    "vht_mu_beamformee": false,
                    "vht_mpdu_len_7991": false,
                    "tx_stbc": false,
                    "shortgi40": false,
                    "vht_mu_beamformer": false,
                    "lsig_txop_prot": false
                },
                "2d4g": {
                    "shortgi20": true,
                    "vht_rx_ldpc": false,
                    "vht_sounding_dimensions_1": false,
                    "ldpc": true,
                    "ht_40": true,
                    "smps_dynamic": true,
                    "vht_shortgi80": false,
                    "vht_rx_stbc_4": false,
                    "vht_txops_ps": false,
                    "eht_320": false,
                    "eht_supported": false,
                    "vht_max_ampdu_len_exp4": false,
                    "vht_max_ampdu_len_exp6": false,
                    "smps_static": false,
                    "vht_rx_antenna_consistency": false,
                    "vht_shortgi160": false,
                    "he_40": false,
                    "vht_tx_stbc": false,
                    "he_supported": false,
                    "vht_ext_nss_bw_3": false,
                    "delayed_ba": false,
                    "ht_20": true,
                    "vht_ext_nss_bw_2": false,
                    "vht_ext_nss_bw_1": false,
                    "vht_beamformee_sts_1": false,
                    "vht_max_ampdu_len_exp3": false,
                    "vht_su_beamformer": false,
                    "vht_tx_antenna_consistency": false,
                    "he_80": false,
                    "vht_rx_stbc_3": false,
                    "vht_max_ampdu_len_exp7": false,
                    "vht_max_ampdu_len_exp1": false,
                    "he_160": false,
                    "vht_max_ampdu_len_exp5": false,
                    "rx_stbc_3": false,
                    "vht_htc": false,
                    "vht_mpdu_len_11454": false,
                    "vht_max_ampdu_len_exp2": false,
                    "vht_rx_stbc_1": false,
                    "rx_stbc_2": false,
                    "vht_sounding_dimensions_3": false,
                    "max_amsdu_7935": false,
                    "vht_su_beamformee": false,
                    "dsss_cck_40": true,
                    "vht_80_80": false,
                    "vht_160": false,
                    "vht_sounding_dimensions_2": false,
                    "psmp": false,
                    "vht_80": false,
                    "vht_beamformee_sts_3": false,
                    "vht_beamformee_sts_2": false,
                    "supported": true,
                    "greenfield": false,
                    "vht_rx_stbc_2": false,
                    "rx_stbc_1": true,
                    "vht_mu_beamformee": false,
                    "vht_mpdu_len_7991": false,
                    "tx_stbc": true,
                    "shortgi40": true,
                    "vht_mu_beamformer": false,
                    "lsig_txop_prot": false
                },
                "60g": {
                    "shortgi20": false,
                    "vht_rx_ldpc": false,
                    "vht_sounding_dimensions_1": false,
                    "ldpc": false,
                    "ht_40": false,
                    "smps_dynamic": false,
                    "vht_shortgi80": false,
                    "vht_rx_stbc_4": false,
                    "vht_txops_ps": false,
                    "eht_320": false,
                    "eht_supported": false,
                    "vht_max_ampdu_len_exp4": false,
                    "vht_max_ampdu_len_exp6": false,
                    "smps_static": false,
                    "vht_rx_antenna_consistency": false,
                    "vht_shortgi160": false,
                    "he_40": false,
                    "vht_tx_stbc": false,
                    "he_supported": false,
                    "vht_ext_nss_bw_3": false,
                    "delayed_ba": false,
                    "ht_20": false,
                    "vht_ext_nss_bw_2": false,
                    "vht_ext_nss_bw_1": false,
                    "vht_beamformee_sts_1": false,
                    "vht_max_ampdu_len_exp3": false,
                    "vht_su_beamformer": false,
                    "vht_tx_antenna_consistency": false,
                    "he_80": false,
                    "vht_rx_stbc_3": false,
                    "vht_max_ampdu_len_exp7": false,
                    "vht_max_ampdu_len_exp1": false,
                    "he_160": false,
                    "vht_max_ampdu_len_exp5": false,
                    "rx_stbc_3": false,
                    "vht_htc": false,
                    "vht_mpdu_len_11454": false,
                    "vht_max_ampdu_len_exp2": false,
                    "vht_rx_stbc_1": false,
                    "rx_stbc_2": false,
                    "vht_sounding_dimensions_3": false,
                    "max_amsdu_7935": false,
                    "vht_su_beamformee": false,
                    "dsss_cck_40": false,
                    "vht_80_80": false,
                    "vht_160": false,
                    "vht_sounding_dimensions_2": false,
                    "psmp": false,
                    "vht_80": false,
                    "vht_beamformee_sts_3": false,
                    "vht_beamformee_sts_2": false,
                    "supported": false,
                    "greenfield": false,
                    "vht_rx_stbc_2": false,
                    "rx_stbc_1": false,
                    "vht_mu_beamformee": false,
                    "vht_mpdu_len_7991": false,
                    "tx_stbc": false,
                    "shortgi40": false,
                    "vht_mu_beamformer": false,
                    "lsig_txop_prot": false
                }
            },
            "name": "2.4G",
            "id": 0,
            "config": {
                "channel_width": "20",
                "band": "2d4g",
                "secondary_channel": 0,
                "ht": {
                    "greenfield": false,
                    "shortgi20": true,
                    "vht_rx_ldpc": false,
                    "ldpc": false,
                    "vht_rx_stbc": "disabled",
                    "vht_shortgi80": false,
                    "vht_mu_beamformer": false,
                    "vht_sounding_dimensions": "disabled",
                    "ht_enabled": true,
                    "rx_stbc": "1",
                    "dsss_cck_40": false,
                    "tx_stbc": true,
                    "ac_enabled": false,
                    "smps": "disabled",
                    "vht_shortgi160": false,
                    "vht_beamformee_sts": "disabled",
                    "vht_tx_stbc": false,
                    "vht_su_beamformee": false,
                    "vht_su_beamformer": false,
                    "delayed_ba": false,
                    "vht_tx_antenna_consistency": false,
                    "max_amsdu_7935": false,
                    "vht_max_ampdu_len_exp": 0,
                    "vht_max_mpdu_len": "default",
                    "psmp": false,
                    "shortgi40": true,
                    "vht_rx_antenna_consistency": false,
                    "lsig_txop_prot": false
                },
                "dfs_enabled": false,
                "eht": {
                    "enabled": false,
                    "su_beamformer": false,
                    "su_beamformee": false,
                    "mu_beamformer": false
                },
                "he": {
                    "enabled": false,
                    "su_beamformee": false,
                    "twt_responder": false,
                    "su_beamformer": false,
                    "twt_required": false,
                    "mu_beamformer": false
                },
                "primary_channel": 0
            },
            "status": {
                "dfs_cac_remaining_time": 0,
                "dfs_disabled": false,
                "channel_width": "20",
                "state": "active",
                "secondary_channel": 0,
                "primary_channel": 6
            }
        },
        {
            "capabilities": {
                "6g": {
                    "shortgi20": false,
                    "vht_rx_ldpc": false,
                    "vht_sounding_dimensions_1": false,
                    "ldpc": false,
                    "ht_40": false,
                    "smps_dynamic": false,
                    "vht_shortgi80": false,
                    "vht_rx_stbc_4": false,
                    "vht_txops_ps": false,
                    "eht_320": false,
                    "eht_supported": false,
                    "vht_max_ampdu_len_exp4": false,
                    "vht_max_ampdu_len_exp6": false,
                    "smps_static": false,
                    "vht_rx_antenna_consistency": false,
                    "vht_shortgi160": false,
                    "he_40": false,
                    "vht_tx_stbc": false,
                    "he_supported": false,
                    "vht_ext_nss_bw_3": false,
                    "delayed_ba": false,
                    "ht_20": false,
                    "vht_ext_nss_bw_2": false,
                    "vht_ext_nss_bw_1": false,
                    "vht_beamformee_sts_1": false,
                    "vht_max_ampdu_len_exp3": false,
                    "vht_su_beamformer": false,
                    "vht_tx_antenna_consistency": false,
                    "he_80": false,
                    "vht_rx_stbc_3": false,
                    "vht_max_ampdu_len_exp7": false,
                    "vht_max_ampdu_len_exp1": false,
                    "he_160": false,
                    "vht_max_ampdu_len_exp5": false,
                    "rx_stbc_3": false,
                    "vht_htc": false,
                    "vht_mpdu_len_11454": false,
                    "vht_max_ampdu_len_exp2": false,
                    "vht_rx_stbc_1": false,
                    "rx_stbc_2": false,
                    "vht_sounding_dimensions_3": false,
                    "max_amsdu_7935": false,
                    "vht_su_beamformee": false,
                    "dsss_cck_40": false,
                    "vht_80_80": false,
                    "vht_160": false,
                    "vht_sounding_dimensions_2": false,
                    "psmp": false,
                    "vht_80": false,
                    "vht_beamformee_sts_3": false,
                    "vht_beamformee_sts_2": false,
                    "supported": false,
                    "greenfield": false,
                    "vht_rx_stbc_2": false,
                    "rx_stbc_1": false,
                    "vht_mu_beamformee": false,
                    "vht_mpdu_len_7991": false,
                    "tx_stbc": false,
                    "shortgi40": false,
                    "vht_mu_beamformer": false,
                    "lsig_txop_prot": false
                },
                "5g": {
                    "shortgi20": true,
                    "vht_rx_ldpc": true,
                    "vht_sounding_dimensions_1": true,
                    "ldpc": true,
                    "ht_40": true,
                    "smps_dynamic": true,
                    "vht_shortgi80": true,
                    "vht_rx_stbc_4": false,
                    "vht_txops_ps": false,
                    "eht_320": false,
                    "eht_supported": false,
                    "vht_max_ampdu_len_exp4": true,
                    "vht_max_ampdu_len_exp6": true,
                    "smps_static": false,
                    "vht_rx_antenna_consistency": true,
                    "vht_shortgi160": true,
                    "he_40": false,
                    "vht_tx_stbc": true,
                    "he_supported": false,
                    "vht_ext_nss_bw_3": false,
                    "delayed_ba": false,
                    "ht_20": true,
                    "vht_ext_nss_bw_2": true,
                    "vht_ext_nss_bw_1": false,
                    "vht_beamformee_sts_1": true,
                    "vht_max_ampdu_len_exp3": true,
                    "vht_su_beamformer": true,
                    "vht_tx_antenna_consistency": true,
                    "he_80": false,
                    "vht_rx_stbc_3": false,
                    "vht_max_ampdu_len_exp7": true,
                    "vht_max_ampdu_len_exp1": true,
                    "he_160": false,
                    "vht_max_ampdu_len_exp5": true,
                    "rx_stbc_3": false,
                    "vht_htc": false,
                    "vht_mpdu_len_11454": true,
                    "vht_max_ampdu_len_exp2": true,
                    "vht_rx_stbc_1": true,
                    "rx_stbc_2": false,
                    "vht_sounding_dimensions_3": true,
                    "max_amsdu_7935": true,
                    "vht_su_beamformee": true,
                    "dsss_cck_40": true,
                    "vht_80_80": false,
                    "vht_160": false,
                    "vht_sounding_dimensions_2": true,
                    "psmp": false,
                    "vht_80": true,
                    "vht_beamformee_sts_3": true,
                    "vht_beamformee_sts_2": true,
                    "supported": true,
                    "greenfield": false,
                    "vht_rx_stbc_2": false,
                    "rx_stbc_1": true,
                    "vht_mu_beamformee": true,
                    "vht_mpdu_len_7991": true,
                    "tx_stbc": true,
                    "shortgi40": true,
                    "vht_mu_beamformer": true,
                    "lsig_txop_prot": false
                },
                "2d4g": {
                    "shortgi20": false,
                    "vht_rx_ldpc": false,
                    "vht_sounding_dimensions_1": false,
                    "ldpc": false,
                    "ht_40": false,
                    "smps_dynamic": false,
                    "vht_shortgi80": false,
                    "vht_rx_stbc_4": false,
                    "vht_txops_ps": false,
                    "eht_320": false,
                    "eht_supported": false,
                    "vht_max_ampdu_len_exp4": false,
                    "vht_max_ampdu_len_exp6": false,
                    "smps_static": false,
                    "vht_rx_antenna_consistency": false,
                    "vht_shortgi160": false,
                    "he_40": false,
                    "vht_tx_stbc": false,
                    "he_supported": false,
                    "vht_ext_nss_bw_3": false,
                    "delayed_ba": false,
                    "ht_20": false,
                    "vht_ext_nss_bw_2": false,
                    "vht_ext_nss_bw_1": false,
                    "vht_beamformee_sts_1": false,
                    "vht_max_ampdu_len_exp3": false,
                    "vht_su_beamformer": false,
                    "vht_tx_antenna_consistency": false,
                    "he_80": false,
                    "vht_rx_stbc_3": false,
                    "vht_max_ampdu_len_exp7": false,
                    "vht_max_ampdu_len_exp1": false,
                    "he_160": false,
                    "vht_max_ampdu_len_exp5": false,
                    "rx_stbc_3": false,
                    "vht_htc": false,
                    "vht_mpdu_len_11454": false,
                    "vht_max_ampdu_len_exp2": false,
                    "vht_rx_stbc_1": false,
                    "rx_stbc_2": false,
                    "vht_sounding_dimensions_3": false,
                    "max_amsdu_7935": false,
                    "vht_su_beamformee": false,
                    "dsss_cck_40": false,
                    "vht_80_80": false,
                    "vht_160": false,
                    "vht_sounding_dimensions_2": false,
                    "psmp": false,
                    "vht_80": false,
                    "vht_beamformee_sts_3": false,
                    "vht_beamformee_sts_2": false,
                    "supported": false,
                    "greenfield": false,
                    "vht_rx_stbc_2": false,
                    "rx_stbc_1": false,
                    "vht_mu_beamformee": false,
                    "vht_mpdu_len_7991": false,
                    "tx_stbc": false,
                    "shortgi40": false,
                    "vht_mu_beamformer": false,
                    "lsig_txop_prot": false
                },
                "60g": {
                    "shortgi20": false,
                    "vht_rx_ldpc": false,
                    "vht_sounding_dimensions_1": false,
                    "ldpc": false,
                    "ht_40": false,
                    "smps_dynamic": false,
                    "vht_shortgi80": false,
                    "vht_rx_stbc_4": false,
                    "vht_txops_ps": false,
                    "eht_320": false,
                    "eht_supported": false,
                    "vht_max_ampdu_len_exp4": false,
                    "vht_max_ampdu_len_exp6": false,
                    "smps_static": false,
                    "vht_rx_antenna_consistency": false,
                    "vht_shortgi160": false,
                    "he_40": false,
                    "vht_tx_stbc": false,
                    "he_supported": false,
                    "vht_ext_nss_bw_3": false,
                    "delayed_ba": false,
                    "ht_20": false,
                    "vht_ext_nss_bw_2": false,
                    "vht_ext_nss_bw_1": false,
                    "vht_beamformee_sts_1": false,
                    "vht_max_ampdu_len_exp3": false,
                    "vht_su_beamformer": false,
                    "vht_tx_antenna_consistency": false,
                    "he_80": false,
                    "vht_rx_stbc_3": false,
                    "vht_max_ampdu_len_exp7": false,
                    "vht_max_ampdu_len_exp1": false,
                    "he_160": false,
                    "vht_max_ampdu_len_exp5": false,
                    "rx_stbc_3": false,
                    "vht_htc": false,
                    "vht_mpdu_len_11454": false,
                    "vht_max_ampdu_len_exp2": false,
                    "vht_rx_stbc_1": false,
                    "rx_stbc_2": false,
                    "vht_sounding_dimensions_3": false,
                    "max_amsdu_7935": false,
                    "vht_su_beamformee": false,
                    "dsss_cck_40": false,
                    "vht_80_80": false,
                    "vht_160": false,
                    "vht_sounding_dimensions_2": false,
                    "psmp": false,
                    "vht_80": false,
                    "vht_beamformee_sts_3": false,
                    "vht_beamformee_sts_2": false,
                    "supported": false,
                    "greenfield": false,
                    "vht_rx_stbc_2": false,
                    "rx_stbc_1": false,
                    "vht_mu_beamformee": false,
                    "vht_mpdu_len_7991": false,
                    "tx_stbc": false,
                    "shortgi40": false,
                    "vht_mu_beamformer": false,
                    "lsig_txop_prot": false
                }
            },
            "name": "5G",
            "id": 1,
            "config": {
                "channel_width": "80",
                "band": "5g",
                "secondary_channel": 0,
                "ht": {
                    "greenfield": false,
                    "shortgi20": true,
                    "vht_rx_ldpc": true,
                    "ldpc": true,
                    "vht_rx_stbc": "1",
                    "vht_shortgi80": true,
                    "vht_mu_beamformer": true,
                    "vht_sounding_dimensions": "3",
                    "ht_enabled": true,
                    "rx_stbc": "1",
                    "dsss_cck_40": true,
                    "tx_stbc": true,
                    "ac_enabled": true,
                    "smps": "disabled",
                    "vht_shortgi160": true,
                    "vht_beamformee_sts": "3",
                    "vht_tx_stbc": true,
                    "vht_su_beamformee": true,
                    "vht_su_beamformer": true,
                    "delayed_ba": false,
                    "vht_tx_antenna_consistency": true,
                    "max_amsdu_7935": false,
                    "vht_max_ampdu_len_exp": 0,
                    "vht_max_mpdu_len": "11454",
                    "psmp": false,
                    "shortgi40": true,
                    "vht_rx_antenna_consistency": true,
                    "lsig_txop_prot": false
                },
                "dfs_enabled": false,
                "eht": {
                    "enabled": false,
                    "su_beamformer": false,
                    "su_beamformee": false,
                    "mu_beamformer": false
                },
                "he": {
                    "enabled": false,
                    "su_beamformee": false,
                    "twt_responder": false,
                    "su_beamformer": false,
                    "twt_required": false,
                    "mu_beamformer": false
                },
                "primary_channel": 0
            },
            "status": {
                "dfs_cac_remaining_time": 0,
                "dfs_disabled": true,
                "channel_width": "80",
                "state": "active",
                "secondary_channel": 44,
                "primary_channel": 48
            }
        }
    ]
}